{
  "2026-05-22": {
    "total_kwh": 224.6,
    "hourly": [
      0.0,
      0.0,
      0.0,
      0.0,
      0.0,
      0.0,
      0.0,
      2.01,
      8.62,
      18.02,
      22.11,
      45.39,
      44.97,
      25.1,
      34.09,
      18.64,
      5.44,
      0.21,
      0.0,
      0.0,
      0.0,
      0.0,
      0.0,
      0.0
    ],
    "irradiation": [
      0.0,
      0,
      0,
      0,
      0,
      0,
      0,
      37.0,
      184.0,
      340.0,
      467.0,
      541.0,
      552.0,
      500.0,
      385.0,
      235.0,
      100.0,
      4.0,
      0,
      0,
      0,
      0,
      0,
      0
    ],
    "last_updated": "2026-05-22 21:54 SAST",
    "last_hour": 17
  },
  "2026-05-23": {
    "total_kwh": 237.21,
    "hourly": [
      0.0,
      0.0,
      0.0,
      0.0,
      0.0,
      0.0,
      0.0,
      2.38,
      9.63,
      22.54,
      27.9,
      31.79,
      38.96,
      44.8,
      34.03,
      20.06,
      4.69,
      0.43,
      0.0,
      0.0,
      0.0,
      0.0,
      0.0,
      0.0
    ],
    "irradiation": [
      0.0,
      0,
      0,
      0,
      0,
      0,
      0,
      35.0,
      185.0,
      340.0,
      458.0,
      517.0,
      512.0,
      466.0,
      385.0,
      257.0,
      100.0,
      3.0,
      0,
      0,
      0,
      0,
      0,
      0
    ],
    "last_updated": "2026-05-23 22:18 SAST",
    "last_hour": 17
  },
  "2026-05-24": {
    "total_kwh": 265.6,
    "hourly": [
      0.0,
      0.0,
      0.0,
      0.0,
      0.0,
      0.0,
      0.01,
      1.8,
      8.18,
      23.35,
      38.03,
      47.06,
      48.2,
      44.66,
      32.92,
      16.91,
      4.1,
      0.38,
      0.0,
      0.0,
      0.0,
      0.0,
      0.0,
      0.0
    ],
    "irradiation": [
      0.0,
      0,
      0,
      0,
      0,
      0,
      0,
      31.0,
      152.0,
      296.0,
      439.0,
      529.0,
      542.0,
      504.0,
      400.0,
      250.0,
      96.0,
      3.0,
      0,
      0,
      0,
      0,
      0,
      0
    ],
    "last_updated": "2026-05-24 22:45 SAST",
    "last_hour": 17
  },
  "2026-05-25": {
    "total_kwh": 240.45,
    "hourly": [
      0.0,
      0.0,
      0.0,
      0.0,
      0.0,
      0.0,
      0.0,
      1.95,
      10.99,
      29.26,
      36.77,
      34.84,
      37.72,
      36.97,
      29.05,
      17.91,
      4.62,
      0.37,
      0.0,
      0.0,
      0.0,
      0.0,
      0.0,
      0.0
    ],
    "irradiation": [
      0.0,
      0,
      0,
      0,
      0,
      0,
      0,
      34.0,
      176.0,
      320.0,
      451.0,
      517.0,
      498.0,
      413.0,
      371.0,
      254.0,
      99.0,
      3.0,
      0,
      0,
      0,
      0,
      0,
      0
    ],
    "last_updated": "2026-05-25 22:03 SAST",
    "last_hour": 17
  },
  "2026-05-26": {
    "total_kwh": 245.85,
    "hourly": [
      0.0,
      0.0,
      0.0,
      0.0,
      0.0,
      0.0,
      0.0,
      2.06,
      7.69,
      21.68,
      36.3,
      45.61,
      40.82,
      42.76,
      28.72,
      14.79,
      5.04,
      0.38,
      0.0,
      0.0,
      0.0,
      0.0,
      0.0,
      0.0
    ],
    "irradiation": [
      0.0,
      0,
      0,
      0,
      0,
      0,
      0,
      31.0,
      182.0,
      326.0,
      444.0,
      531.0,
      545.0,
      501.0,
      388.0,
      244.0,
      87.0,
      3.0,
      0,
      0,
      0,
      0,
      0,
      0
    ],
    "last_updated": "2026-05-26 22:37 SAST",
    "last_hour": 17
  },
  "2026-05-27": {
    "total_kwh": 254.89,
    "hourly": [
      0.0,
      0.0,
      0.0,
      0.0,
      0.0,
      0.0,
      0.0,
      1.56,
      7.47,
      21.57,
      35.88,
      44.57,
      46.97,
      43.06,
      32.22,
      16.97,
      4.3,
      0.32,
      0.0,
      0.0,
      0.0,
      0.0,
      0.0,
      0.0
    ],
    "irradiation": [
      0.0,
      0,
      0,
      0,
      0,
      0,
      0,
      24.0,
      145.0,
      303.0,
      444.0,
      513.0,
      533.0,
      480.0,
      398.0,
      259.0,
      99.0,
      3.0,
      0,
      0,
      0,
      0,
      0,
      0
    ],
    "last_updated": "2026-05-27 23:11 SAST",
    "last_hour": 17
  },
  "2026-05-28": {
    "total_kwh": 254.87,
    "hourly": [
      0.0,
      0.0,
      0.0,
      0.0,
      0.0,
      0.0,
      0.0,
      2.61,
      7.87,
      23.19,
      36.36,
      43.59,
      45.64,
      41.56,
      31.8,
      16.72,
      5.13,
      0.4,
      0.0,
      0.0,
      0.0,
      0.0,
      0.0,
      0.0
    ],
    "irradiation": [
      0.0,
      0,
      0,
      0,
      0,
      0,
      0,
      22.0,
      139.0,
      318.0,
      427.0,
      517.0,
      517.0,
      464.0,
      339.0,
      242.0,
      91.0,
      3.0,
      0,
      0,
      0,
      0,
      0,
      0
    ],
    "last_updated": "2026-05-28 21:46 SAST",
    "last_hour": 17
  },
  "2026-05-29": {
    "total_kwh": 214.54,
    "hourly": [
      0,
      0,
      0,
      0,
      0,
      0,
      0,
      1.13,
      4.46,
      12.52,
      20.51,
      39.43,
      41.92,
      43.45,
      28.63,
      16.81,
      5.39,
      0.29,
      0,
      0,
      0,
      0,
      0.0,
      0.0
    ],
    "irradiation": [
      0.0,
      0,
      0,
      0,
      0,
      0,
      0,
      20.0,
      28.0,
      111.0,
      303.0,
      417.0,
      515.0,
      451.0,
      320.0,
      172.0,
      73.0,
      2.0,
      0,
      0,
      0,
      0,
      0,
      0
    ],
    "last_updated": "2026-05-29 22:38 SAST",
    "last_hour": 17
  },
  "2026-05-30": {
    "total_kwh": 249.82,
    "hourly": [
      0.0,
      0.0,
      0.0,
      0.0,
      0.0,
      0.0,
      0.0,
      1.41,
      6.54,
      21.06,
      35.71,
      44.32,
      46.44,
      41.98,
      31.39,
      16.3,
      4.29,
      0.38,
      0.0,
      0.0,
      0.0,
      0.0,
      0.0,
      0.0
    ],
    "irradiation": [
      0.0,
      0,
      0,
      0,
      0,
      0,
      0,
      29.0,
      170.0,
      322.0,
      448.0,
      525.0,
      546.0,
      503.0,
      403.0,
      261.0,
      97.0,
      3.0,
      0,
      0,
      0,
      0,
      0,
      0
    ],
    "last_updated": "2026-05-30 22:16 SAST",
    "last_hour": 17
  },
  "2026-05-31": {
    "total_kwh": 240.88,
    "hourly": [
      0.0,
      0.0,
      0.0,
      0.0,
      0.0,
      0.0,
      0.01,
      1.53,
      6.94,
      20.43,
      34.03,
      42.56,
      44.63,
      40.28,
      30.14,
      15.71,
      4.28,
      0.34,
      0.0,
      0.0,
      0.0,
      0.0,
      0.0,
      0.0
    ],
    "irradiation": [
      0.0,
      0,
      0,
      0,
      0,
      0,
      0,
      29.0,
      175.0,
      330.0,
      448.0,
      525.0,
      541.0,
      498.0,
      401.0,
      258.0,
      96.0,
      3.0,
      0,
      0,
      0,
      0,
      0,
      0
    ],
    "last_updated": "2026-05-31 22:20 SAST",
    "last_hour": 17
  },
  "2026-06-01": {
    "total_kwh": 234.47,
    "hourly": [
      0.0,
      0.0,
      0.0,
      0.0,
      0.0,
      0.0,
      0.0,
      1.63,
      7.56,
      20.08,
      33.15,
      40.92,
      43.03,
      38.8,
      28.87,
      15.47,
      4.75,
      0.21,
      0.0,
      0.0,
      0.0,
      0.0,
      0.0,
      0.0
    ],
    "irradiation": [
      0.0,
      0,
      0,
      0,
      0,
      0,
      0,
      28.0,
      172.0,
      330.0,
      454.0,
      528.0,
      543.0,
      500.0,
      401.0,
      257.0,
      95.0,
      2.0,
      0,
      0,
      0,
      0,
      0,
      0
    ],
    "last_updated": "2026-06-01 20:38 SAST",
    "last_hour": 17
  },
  "2026-06-02": {
    "total_kwh": 231.81,
    "hourly": [
      0.0,
      0.0,
      0.0,
      0.0,
      0.0,
      0.0,
      0.0,
      2.08,
      10.29,
      27.8,
      28.57,
      34.86,
      41.35,
      35.99,
      29.04,
      15.42,
      6.0,
      0.4,
      0.0,
      0.0,
      0.0,
      0.0,
      0.0,
      0.0
    ],
    "irradiation": [
      0.0,
      0,
      0,
      0,
      0,
      0,
      0,
      25.0,
      157.0,
      291.0,
      403.0,
      463.0,
      483.0,
      435.0,
      344.0,
      233.0,
      84.0,
      2.0,
      0,
      0,
      0,
      0,
      0,
      0
    ],
    "last_updated": "2026-06-02 22:49 SAST",
    "last_hour": 17
  },
  "2026-06-03": {
    "total_kwh": 35.23,
    "hourly": [
      0.0,
      0.0,
      0.0,
      0.0,
      0.0,
      0.0,
      0.0,
      0.17,
      1.16,
      6.39,
      10.74,
      5.61,
      4.39,
      3.44,
      1.97,
      1.09,
      0.26,
      0.01,
      0.0,
      0.0,
      0.0,
      0.0,
      0.0,
      0.0
    ],
    "irradiation": [
      0.0,
      0,
      0,
      0,
      0,
      0,
      0,
      7.0,
      22.0,
      55.0,
      37.0,
      41.0,
      90.0,
      50.0,
      23.0,
      13.0,
      3.0,
      0,
      0,
      0,
      0,
      0,
      0,
      0
    ],
    "last_updated": "2026-06-03 23:49 SAST",
    "last_hour": 17
  },
  "2026-06-04": {
    "total_kwh": 73.71,
    "hourly": [
      0.0,
      0.0,
      0.0,
      0.0,
      0.0,
      0.0,
      0.0,
      0.29,
      2.24,
      3.21,
      5.18,
      11.78,
      14.4,
      12.11,
      13.09,
      7.56,
      3.79,
      0.05,
      0.0,
      0.0,
      0.0,
      0.0,
      0.0,
      0.0
    ],
    "irradiation": [
      0.0,
      0,
      0,
      0,
      0,
      0,
      0,
      7.0,
      43.0,
      82.0,
      158.0,
      177.0,
      141.0,
      178.0,
      197.0,
      63.0,
      29.0,
      1.0,
      0,
      0,
      0,
      0,
      0,
      0
    ],
    "last_updated": "2026-06-04 22:56 SAST",
    "last_hour": 17
  },
  "2026-06-05": {
    "total_kwh": 242.67,
    "hourly": [
      0.0,
      0.0,
      0.0,
      0.0,
      0.0,
      0.0,
      0.0,
      1.42,
      11.09,
      18.94,
      33.82,
      45.78,
      44.01,
      34.26,
      30.41,
      17.25,
      5.3,
      0.38,
      0.0,
      0.0,
      0.0,
      0.0,
      0.0,
      0.0
    ],
    "irradiation": [
      0.0,
      0,
      0,
      0,
      0,
      0,
      0,
      22.0,
      154.0,
      299.0,
      403.0,
      443.0,
      499.0,
      459.0,
      372.0,
      228.0,
      89.0,
      2.0,
      0,
      0,
      0,
      0,
      0,
      0
    ],
    "last_updated": "2026-06-05 21:54 SAST",
    "last_hour": 17
  },
  "2026-06-06": {
    "total_kwh": 219.67,
    "hourly": [
      0.0,
      0.0,
      0.0,
      0.0,
      0.0,
      0.0,
      0.0,
      1.4,
      9.99,
      21.79,
      29.89,
      34.63,
      34.36,
      32.86,
      34.16,
      16.56,
      3.77,
      0.26,
      0.0,
      0.0,
      0.0,
      0.0,
      0.0,
      0.0
    ],
    "irradiation": [
      0.0,
      0,
      0,
      0,
      0,
      0,
      0,
      25.0,
      164.0,
      317.0,
      404.0,
      405.0,
      370.0,
      397.0,
      376.0,
      258.0,
      92.0,
      2.0,
      0,
      0,
      0,
      0,
      0,
      0
    ],
    "last_updated": "2026-06-06 21:22 SAST",
    "last_hour": 17
  },
  "2026-06-07": {
    "total_kwh": 226.25,
    "hourly": [
      0.0,
      0.0,
      0.0,
      0.0,
      0.0,
      0.0,
      0.0,
      1.03,
      5.54,
      19.46,
      33.66,
      42.22,
      39.93,
      35.56,
      28.5,
      14.7,
      5.22,
      0.42,
      0.0,
      0.0,
      0.0,
      0.0,
      0.0,
      0.0
    ],
    "irradiation": [
      0.0,
      0,
      0,
      0,
      0,
      0,
      0,
      20.0,
      154.0,
      294.0,
      436.0,
      519.0,
      535.0,
      493.0,
      395.0,
      252.0,
      92.0,
      2.0,
      0,
      0,
      0,
      0,
      0,
      0
    ],
    "last_updated": "2026-06-07 22:12 SAST",
    "last_hour": 17
  },
  "2026-06-08": {
    "total_kwh": 171.4,
    "hourly": [
      0.0,
      0.0,
      0.0,
      0.0,
      0.0,
      0.0,
      0.0,
      2.7,
      11.07,
      20.49,
      22.63,
      40.53,
      36.12,
      19.4,
      8.99,
      7.58,
      1.82,
      0.07,
      0.0,
      0.0,
      0.0,
      0.0,
      0.0,
      0.0
    ],
    "irradiation": [
      0.0,
      0,
      0,
      0,
      0,
      0,
      0,
      15.0,
      145.0,
      307.0,
      323.0,
      172.0,
      207.0,
      176.0,
      98.0,
      123.0,
      15.0,
      1.0,
      0,
      0,
      0,
      0,
      0,
      0
    ],
    "last_updated": "2026-06-08 22:14 SAST",
    "last_hour": 17
  },
  "2026-06-09": {
    "total_kwh": 224.09,
    "hourly": [
      0.0,
      0.0,
      0.0,
      0.0,
      0.0,
      0.0,
      0.0,
      0.92,
      5.84,
      15.61,
      31.2,
      40.8,
      44.12,
      39.13,
      26.27,
      16.1,
      3.79,
      0.3,
      0.0,
      0.0,
      0.0,
      0.0,
      0.0,
      0.0
    ],
    "irradiation": [
      0.0,
      0,
      0,
      0,
      0,
      0,
      0,
      16.0,
      122.0,
      268.0,
      357.0,
      415.0,
      425.0,
      437.0,
      358.0,
      208.0,
      81.0,
      2.0,
      0,
      0,
      0,
      0,
      0,
      0
    ],
    "last_updated": "2026-06-09 21:13 SAST",
    "last_hour": 17
  },
  "2026-06-10": {
    "total_kwh": 223.45,
    "hourly": [
      0.0,
      0.0,
      0.0,
      0.0,
      0.0,
      0.0,
      0.0,
      1.31,
      5.89,
      9.9,
      29.76,
      42.1,
      44.75,
      40.33,
      29.82,
      15.09,
      4.18,
      0.32,
      0.0,
      0.0,
      0.0,
      0.0,
      0.0,
      0.0
    ],
    "irradiation": [
      0.0,
      0,
      0,
      0,
      0,
      0,
      0,
      16.0,
      107.0,
      229.0,
      369.0,
      453.0,
      500.0,
      472.0,
      389.0,
      252.0,
      93.0,
      2.0,
      0,
      0,
      0,
      0,
      0,
      0
    ],
    "last_updated": "2026-06-10 23:24 SAST",
    "last_hour": 17
  },
  "2026-06-11": {
    "total_kwh": 168.4,
    "hourly": [
      0.0,
      0.0,
      0.0,
      0.0,
      0.0,
      0.0,
      0.0,
      1.64,
      9.64,
      18.68,
      23.89,
      25.84,
      23.35,
      22.64,
      17.85,
      19.3,
      5.28,
      0.29,
      0.0,
      0.0,
      0.0,
      0.0,
      0.0,
      0.0
    ],
    "irradiation": [
      0.0,
      0,
      0,
      0,
      0,
      0,
      0,
      18.0,
      151.0,
      297.0,
      417.0,
      481.0,
      516.0,
      494.0,
      391.0,
      252.0,
      90.0,
      2.0,
      0,
      0,
      0,
      0,
      0,
      0
    ],
    "last_updated": "2026-06-11 21:35 SAST",
    "last_hour": 17
  },
  "2026-06-12": {
    "total_kwh": 168.22,
    "hourly": [
      0.0,
      0.0,
      0.0,
      0.0,
      0.0,
      0.0,
      0.0,
      0.93,
      5.45,
      18.86,
      32.25,
      28.02,
      22.84,
      14.59,
      19.59,
      18.4,
      6.99,
      0.3,
      0.0,
      0.0,
      0.0,
      0.0,
      0.0,
      0.0
    ],
    "irradiation": [
      0.0,
      0,
      0,
      0,
      0,
      0,
      0,
      20.0,
      149.0,
      259.0,
      363.0,
      390.0,
      364.0,
      393.0,
      331.0,
      192.0,
      81.0,
      2.0,
      0,
      0,
      0,
      0,
      0,
      0
    ],
    "last_updated": "2026-06-12 22:09 SAST",
    "last_hour": 17
  },
  "2026-06-13": {
    "total_kwh": 215.29,
    "hourly": [
      0.0,
      0.0,
      0.0,
      0.0,
      0.0,
      0.0,
      0.0,
      1.53,
      12.84,
      23.45,
      34.75,
      37.59,
      37.37,
      29.83,
      26.26,
      9.86,
      1.79,
      0.02,
      0.0,
      0.0,
      0.0,
      0.0,
      0.0,
      0.0
    ],
    "irradiation": [
      0.0,
      0,
      0,
      0,
      0,
      0,
      0,
      19.0,
      139.0,
      248.0,
      381.0,
      400.0,
      358.0,
      315.0,
      223.0,
      119.0,
      35.0,
      1.0,
      0,
      0,
      0,
      0,
      0,
      0
    ],
    "last_updated": "2026-06-13 22:15 SAST",
    "last_hour": 17
  },
  "2026-06-14": {
    "total_kwh": 239.22,
    "hourly": [
      0.0,
      0.0,
      0.0,
      0.0,
      0.0,
      0.0,
      0.0,
      2.01,
      11.53,
      21.69,
      29.72,
      41.14,
      44.92,
      39.72,
      29.27,
      14.9,
      3.94,
      0.37,
      0.0,
      0.0,
      0.0,
      0.0,
      0.0,
      0.0
    ],
    "irradiation": [
      0.0,
      0,
      0,
      0,
      0,
      0,
      0,
      18.0,
      130.0,
      269.0,
      384.0,
      502.0,
      501.0,
      466.0,
      383.0,
      248.0,
      91.0,
      2.0,
      0,
      0,
      0,
      0,
      0,
      0
    ],
    "last_updated": "2026-06-14 21:25 SAST",
    "last_hour": 17
  },
  "2026-06-15": {
    "total_kwh": 246.11,
    "hourly": [
      0.0,
      0.0,
      0.0,
      0.0,
      0.0,
      0.0,
      0.0,
      1.74,
      7.9,
      19.19,
      30.8,
      41.85,
      45.1,
      42.07,
      30.79,
      22.44,
      4.08,
      0.14,
      0.0,
      0.0,
      0.0,
      0.0,
      0.0,
      0.0
    ],
    "irradiation": [
      0.0,
      0,
      0,
      0,
      0,
      0,
      0,
      14.0,
      118.0,
      261.0,
      325.0,
      353.0,
      442.0,
      384.0,
      268.0,
      166.0,
      65.0,
      1.0,
      0,
      0,
      0,
      0,
      0,
      0
    ],
    "last_updated": "2026-06-15 21:47 SAST",
    "last_hour": 17
  },
  "2026-06-16": {
    "total_kwh": 219.04,
    "hourly": [
      0.0,
      0.0,
      0.0,
      0.0,
      0.0,
      0.0,
      0.0,
      0.89,
      5.55,
      16.95,
      29.54,
      38.86,
      41.44,
      34.13,
      29.61,
      16.89,
      4.94,
      0.24,
      0.0,
      0.0,
      0.0,
      0.0,
      0.0,
      0.0
    ],
    "irradiation": [
      0.0,
      0,
      0,
      0,
      0,
      0,
      0,
      17.0,
      140.0,
      295.0,
      414.0,
      471.0,
      403.0,
      429.0,
      347.0,
      211.0,
      77.0,
      2.0,
      0,
      0,
      0,
      0,
      0,
      0
    ],
    "last_updated": "2026-06-16 23:41 SAST",
    "last_hour": 17
  },
  "2026-06-17": {
    "total_kwh": 221.59,
    "hourly": [
      0.0,
      0.0,
      0.0,
      0.0,
      0.0,
      0.0,
      0.0,
      1.29,
      8.7,
      20.04,
      29.42,
      38.49,
      41.01,
      37.22,
      27.51,
      13.98,
      3.67,
      0.25,
      0.0,
      0.0,
      0.0,
      0.0,
      0.0,
      0.0
    ],
    "irradiation": [
      0.0,
      0,
      0,
      0,
      0,
      0,
      0,
      14.0,
      118.0,
      239.0,
      340.0,
      413.0,
      437.0,
      351.0,
      360.0,
      237.0,
      86.0,
      2.0,
      0,
      0,
      0,
      0,
      0,
      0
    ],
    "last_updated": "2026-06-17 21:25 SAST",
    "last_hour": 17
  },
  "2026-06-18": {
    "total_kwh": 197.85,
    "hourly": [
      0.0,
      0.0,
      0.0,
      0.0,
      0.0,
      0.0,
      0.0,
      1.06,
      5.5,
      16.8,
      29.55,
      24.64,
      38.03,
      37.16,
      33.36,
      8.91,
      2.59,
      0.25,
      0.0,
      0.0,
      0.0,
      0.0,
      0.0,
      0.0
    ],
    "irradiation": [
      0.0,
      0,
      0,
      0,
      0,
      0,
      0,
      14.0,
      110.0,
      229.0,
      364.0,
      454.0,
      397.0,
      312.0,
      242.0,
      165.0,
      68.0,
      1.0,
      0,
      0,
      0,
      0,
      0,
      0
    ],
    "last_updated": "2026-06-18 21:27 SAST",
    "last_hour": 17
  },
  "2026-06-19": {
    "total_kwh": 213.24,
    "hourly": [
      0.0,
      0.0,
      0.0,
      0.0,
      0.0,
      0.0,
      0.0,
      1.05,
      8.16,
      13.8,
      26.34,
      42.18,
      40.77,
      37.81,
      24.44,
      13.62,
      4.83,
      0.24,
      0.0,
      0.0,
      0.0,
      0.0,
      0.0,
      0.0
    ],
    "irradiation": [
      0.0,
      0,
      0,
      0,
      0,
      0,
      0,
      4.0,
      35.0,
      150.0,
      343.0,
      360.0,
      393.0,
      426.0,
      352.0,
      242.0,
      90.0,
      2.0,
      0,
      0,
      0,
      0,
      0,
      0
    ],
    "last_updated": "2026-06-19 22:26 SAST",
    "last_hour": 17
  },
  "2026-06-20": {
    "total_kwh": 203.13,
    "hourly": [
      0.0,
      0.0,
      0.0,
      0.0,
      0.0,
      0.0,
      0.0,
      1.21,
      6.39,
      17.86,
      31.1,
      38.77,
      32.55,
      21.73,
      33.81,
      14.77,
      4.64,
      0.29,
      0.0,
      0.0,
      0.0,
      0.0,
      0.0,
      0.0
    ],
    "irradiation": [
      0.0,
      0,
      0,
      0,
      0,
      0,
      0,
      17.0,
      145.0,
      302.0,
      422.0,
      493.0,
      470.0,
      463.0,
      373.0,
      174.0,
      57.0,
      2.0,
      0,
      0,
      0,
      0,
      0,
      0
    ],
    "last_updated": "2026-06-20 21:25 SAST",
    "last_hour": 17
  },
  "2026-06-21": {
    "total_kwh": 169.92,
    "hourly": [
      0.0,
      0.0,
      0.0,
      0.0,
      0.0,
      0.0,
      0.0,
      1.05,
      6.92,
      17.26,
      25.36,
      26.02,
      29.49,
      25.97,
      17.11,
      15.8,
      4.7,
      0.23,
      0.0,
      0.0,
      0.0,
      0.0,
      0.0,
      0.0
    ],
    "irradiation": [
      0.0,
      0,
      0,
      0,
      0,
      0,
      0,
      14.0,
      125.0,
      279.0,
      402.0,
      479.0,
      485.0,
      438.0,
      317.0,
      208.0,
      77.0,
      2.0,
      0,
      0,
      0,
      0,
      0,
      0
    ],
    "last_updated": "2026-06-21 22:24 SAST",
    "last_hour": 17
  }
}