{
  "search_name": "Bel Essex(Valeo)",
  "slug": "bel-essex-valeo",
  "station_code": "NE=56006848",
  "fetched_at_utc": "2026-06-13T12:24:57.244883",
  "date": "2026-06-13",
  "plant_name": "Bel Essex(Valeo)",
  "total_kwh": 831.41,
  "day_power": 831.41,
  "month_power": 21673.44,
  "total_power": 1130436.62,
  "health_state": 3,
  "hourly_pv": [
    0.0,
    0.0,
    0.0,
    0.0,
    0.0,
    0.0,
    0.0,
    5.08,
    42.62,
    125.38,
    109.86,
    131.71,
    155.09,
    247.94,
    0.0,
    0.0,
    0.0,
    0.0,
    0.0,
    0.0,
    0.0,
    0.0,
    0.0,
    0.0
  ],
  "last_hour": 13
}