{
  "search_name": "BMI park",
  "slug": "bmi-park",
  "station_code": "NE=63713198",
  "fetched_at_utc": "2026-06-11T12:46:19.158993",
  "date": "2026-06-11",
  "plant_name": "BMI park",
  "total_kwh": 1248.63,
  "day_power": 1248.63,
  "month_power": 16683.24,
  "total_power": 728324.3,
  "health_state": 3,
  "hourly_pv": [
    0.0,
    0.0,
    0.0,
    0.0,
    0.0,
    0.0,
    0.0,
    13.22,
    102.9,
    113.83,
    195.09,
    273.9,
    248.35,
    164.64,
    0.0,
    0.0,
    0.0,
    0.0,
    0.0,
    0.0,
    0.0,
    0.0,
    0.0,
    0.0
  ],
  "last_hour": 13
}