{
  "search_name": "Coega Dairy",
  "slug": "coega-dairy",
  "station_code": "NE=51003907",
  "fetched_at_utc": "2026-05-30T12:01:46.265078",
  "date": "2026-05-30",
  "plant_name": "Coega Dairy",
  "total_kwh": 2499.52,
  "day_power": 2499.52,
  "month_power": 71748.55,
  "total_power": 6027835.82,
  "health_state": 3,
  "hourly_pv": [
    0.0,
    0.0,
    0.0,
    0.0,
    0.0,
    0.0,
    0.0,
    25.47,
    161.45,
    334.63,
    462.34,
    531.88,
    538.25,
    0.0,
    0.0,
    0.0,
    0.0,
    0.0,
    0.0,
    0.0,
    0.0,
    0.0,
    0.0,
    0.0
  ],
  "last_hour": 12
}