{
  "search_name": "GM-Hasty Tasty",
  "slug": "gm-hasty-tasty",
  "station_code": "NE=85483210",
  "fetched_at_utc": "2026-06-16T21:41:18.200017",
  "date": "2026-06-16",
  "plant_name": "GM-Hasty Tasty",
  "total_kwh": 519.67,
  "day_power": 519.67,
  "month_power": 7235.93,
  "total_power": 33572.96,
  "health_state": 3,
  "hourly_pv": [
    0.0,
    0.0,
    0.0,
    0.0,
    0.0,
    0.0,
    0.0,
    2.56,
    24.18,
    52.35,
    87.18,
    103.7,
    106.9,
    72.17,
    30.09,
    26.6,
    13.53,
    0.41,
    0.0,
    0.0,
    0.0,
    0.0,
    0.0,
    0.0
  ],
  "last_hour": 17
}