{
  "search_name": "kirkwood spar power meter",
  "slug": "kirkwood-spar",
  "station_code": "NE=64153308",
  "fetched_at_utc": "2026-06-17T07:47:43.058110",
  "date": "2026-06-17",
  "plant_name": "kirkwood spar power meter",
  "total_kwh": 24.32,
  "day_power": 24.32,
  "month_power": 3163.28,
  "total_power": 129449.3,
  "health_state": 3,
  "hourly_pv": [
    0.0,
    0.0,
    0.0,
    0.0,
    0.0,
    0.0,
    0.0,
    1.29,
    8.7,
    0.0,
    0.0,
    0.0,
    0.0,
    0.0,
    0.0,
    0.0,
    0.0,
    0.0,
    0.0,
    0.0,
    0.0,
    0.0,
    0.0,
    0.0
  ],
  "last_hour": 8
}