{
  "search_name": "RDM Somerset West 5MW",
  "slug": "rdm-somerset-west",
  "station_code": "NE=51657840",
  "fetched_at_utc": "2026-06-05T07:09:01.205707",
  "date": "2026-06-05",
  "plant_name": "RDM Somerset West 5MW",
  "total_kwh": 546.28,
  "day_power": 546.28,
  "month_power": 50647.69,
  "total_power": 11587504.45,
  "health_state": 3,
  "hourly_pv": [
    0.0,
    0.0,
    0.0,
    0.0,
    0.0,
    0.0,
    0.0,
    7.13,
    0.0,
    0.0,
    0.0,
    0.0,
    0.0,
    0.0,
    0.0,
    0.0,
    0.0,
    0.0,
    0.0,
    0.0,
    0.0,
    0.0,
    0.0,
    0.0
  ],
  "last_hour": 7
}