{
  "search_name": "RDM Somerset West 5MW",
  "slug": "rdm-somerset-west",
  "station_code": "NE=51657840",
  "fetched_at_utc": "2026-06-06T19:22:51.744277",
  "date": "2026-06-06",
  "plant_name": "RDM Somerset West 5MW",
  "total_kwh": 10805.32,
  "day_power": 10805.32,
  "month_power": 79920.77,
  "total_power": 11616777.53,
  "health_state": 3,
  "hourly_pv": [
    0.0,
    0.0,
    0.0,
    0.0,
    0.0,
    0.0,
    0.0,
    7.66,
    260.01,
    1429.81,
    1529.21,
    1468.25,
    1370.53,
    1152.2,
    1377.34,
    1278.61,
    823.51,
    108.12,
    0.07,
    0.0,
    0.0,
    0.0,
    0.0,
    0.0
  ],
  "last_hour": 18
}