{
  "search_name": "WG Group - Nurture Health",
  "slug": "wg-nurture-health",
  "station_code": "NE=54875772",
  "fetched_at_utc": "2026-06-22T12:15:05.336431",
  "date": "2026-06-22",
  "plant_name": "WG Group - Nurture Health",
  "total_kwh": 71.42,
  "day_power": 71.42,
  "month_power": 1683.44,
  "total_power": 75292.2,
  "health_state": 3,
  "hourly_pv": [
    0.0,
    0.0,
    0.0,
    0.0,
    0.0,
    0.0,
    0.0,
    0.55,
    2.59,
    9.76,
    11.57,
    15.67,
    15.62,
    0.0,
    0.0,
    0.0,
    0.0,
    0.0,
    0.0,
    0.0,
    0.0,
    0.0,
    0.0,
    0.0
  ],
  "last_hour": 12
}